fucknuker/__init__.py
fucknuker/main.py
fuckingnuker-0.1.3.dist-info/METADATA
fuckingnuker-0.1.3.dist-info/WHEEL
fuckingnuker-0.1.3.dist-info/entry_points.txt
fuckingnuker-0.1.3.dist-info/top_level.txt
fuckingnuker-0.1.3.dist-info/RECORD
